combination/mux4_1.v
module mux4_1 (y, x0, x1, x2, x3, c1, c0);
    input x0, x1, x2, x3, c1, c0;
    output y;
    
    wire w_A0, w_A1, w_A2, w_A3;
    wire w_r0, w_r2;

    wire w_N1, w_N0;

    not N1(w_N1, c1);
    not N0(w_N0, c0);

    and A0(w_A0, x0, w_N1, w_N0);
    and A1(w_A1, x1, w_N1, c0);
    and A2(w_A2, x2, c1, w_N0);
    and A3(w_A3, x3, c1, c0);

    or r0(w_r0, w_A0, w_A1);
    or r2(w_r2, w_A2, w_A3);
    or r3(y, w_r0, w_r2);
endmodule

combination/adder.v
module adder (Sum, Cout, Cin, A, B);
    input Cin, A, B;
    output Sum, Cout;

    wire w_xr0, w_A0, w_A1;

    xor xr0(w_xr0, A, B);
    xor xr1 (Sum, Cin, w_xr0);

    and A0(w_A0, w_xr0, Cin);
    and A1(w_A1, A, B);

    or r0(Cout, w_A0, w_A1);
endmodule

combination/1bit_ALU.v
`include "adder.v"
`include "mux4_1.v"

module one_bit_ALU (y, z, Cin, A, B, c1, c0);
    input Cin, A, B, c1, c0;
    output y, z;

    wire w_Sum, w_Cout;
    wire w_A0, w_N0, w_xr0;

    adder Adder1(w_Sum, w_Cout, Cin, A, B);
    and A0(w_A0, A, B);
    not N0(w_N0, A);
    xor xr0(w_xr0, A, B);

    mux4_1 mux1(y, w_Sum, w_A0, w_N0, 1'b0, c1, c0);
    mux4_1 mux2(z, w_Cout, 1'b0, 1'b0, w_xr0, c1, c0);
endmodule

combination/stimulus_1bit_ALU.v
`include "1bit_ALU.v"

module stimulus_1bit_ALU;
    reg Cin, A, B;
    reg c1, c0;

    wire y;
    wire z;

    // instantiate the design block
    one_bit_ALU one_bit_ALU(y, z, Cin, A, B, c1, c0);

    // control the signals that drives the design block
    initial begin
        $dumpfile("1bitALU_TimingDiagram.vcd");
        $dumpvars(0, one_bit_ALU);
        Cin = 1'b0;
        A = 1'b0;
        B = 1'b0;
        c1 = 1'b0;
        c0 = 1'b0;

        // 0+0+0
        #5 begin
            A = 1'b0;
            B = 1'b0;
            Cin = 1'b0;
        end
        // 0+0+1
        #5 begin
            A = 1'b0;
            B = 1'b0;
            Cin = 1'b1;    
        end
        // 0+1+0
        #5 begin
            A = 1'b0;
            B = 1'b1;
            Cin = 1'b0;    
        end
        // 0+1+1
        #5 begin
            A = 1'b0;
            B = 1'b1;
            Cin = 1'b1;
        end
        // 1+0+0
        #5 begin
            A = 1'b1;
            B = 1'b0;
            Cin = 1'b0;
        end
        // 1+0+1
        #5 begin
            A = 1'b1;
            B = 1'b0;
            Cin = 1'b1;
        end
        // 1+1+0
        #5 begin
            A = 1'b1;
            B = 1'b1;
            Cin = 1'b0;
        end
        // 1+1+1
        #5 begin
            A = 1'b1;
            B = 1'b1;
            Cin = 1'b1;
        end

        #5 c0 = 1'b1;

        #5 begin
           A = 1'b0;
           B = 1'b0;
        end

        #5 begin
           A = 1'b0;
           B = 1'b1;
        end

        #5 begin
            A = 1'b1;
            B = 1'b0;
        end
        
        #5 begin
            c1 = 1'b1;
            c0 = 1'b0;
        end
       #5 begin
            A = 1'b0;
            B = 1'b0;
        end
        #5 begin
            A = 1'b0;
            B = 1'b1;
        end
        #5 begin
            A = 1'b1;
            B = 1'b0;
        end
        #5 begin
            A = 1'b1;
            B = 1'b1;
        end
        
        #5 c0 = 1'b1;
        #5 begin
            A = 1'b0;
            B = 1'b0;
        end
        #5 begin
            A = 1'b0;
            B = 1'b1;
        end
        #5 begin
            A = 1'b1;
            B = 1'b0;
        end
        #5 begin
            A = 1'b1;
            B = 1'b1;
        end

        #120 $finish;
    end

    initial
        $monitor($time, " Output Cin=%d A=%d B=%d c1=%d c0=%d y=%d z=%d", 
        Cin, A, B, c1, c0, y, z);
endmodule

combination/1bitALU_TimingDiagram.vcd
$date
	Sun Oct 17 19:49:13 2021
$end
$version
	Icarus Verilog
$end
$timescale
	1s
$end
$scope module stimulus_1bit_ALU $end
$scope module one_bit_ALU $end
$var wire 1 ! A $end
$var wire 1 " B $end
$var wire 1 # Cin $end
$var wire 1 $ c0 $end
$var wire 1 % c1 $end
$var wire 1 & w_A0 $end
$var wire 1 ' w_N0 $end
$var wire 1 ( w_xr0 $end
$var wire 1 ) z $end
$var wire 1 * y $end
$var wire 1 + w_Sum $end
$var wire 1 , w_Cout $end
$scope module Adder1 $end
$var wire 1 ! A $end
$var wire 1 " B $end
$var wire 1 # Cin $end
$var wire 1 , Cout $end
$var wire 1 + Sum $end
$var wire 1 - w_A0 $end
$var wire 1 . w_A1 $end
$var wire 1 / w_xr0 $end
$upscope $end
$scope module mux1 $end
$var wire 1 $ c0 $end
$var wire 1 % c1 $end
$var wire 1 0 w_A0 $end
$var wire 1 1 w_A1 $end
$var wire 1 2 w_A2 $end
$var wire 1 3 w_A3 $end
$var wire 1 4 w_N0 $end
$var wire 1 5 w_N1 $end
$var wire 1 6 w_r0 $end
$var wire 1 7 w_r2 $end
$var wire 1 + x0 $end
$var wire 1 & x1 $end
$var wire 1 ' x2 $end
$var wire 1 8 x3 $end
$var wire 1 * y $end
$upscope $end
$scope module mux2 $end
$var wire 1 $ c0 $end
$var wire 1 % c1 $end
$var wire 1 9 w_A0 $end
$var wire 1 : w_A1 $end
$var wire 1 ; w_A2 $end
$var wire 1 < w_A3 $end
$var wire 1 = w_N0 $end
$var wire 1 > w_N1 $end
$var wire 1 ? w_r0 $end
$var wire 1 @ w_r2 $end
$var wire 1 , x0 $end
$var wire 1 A x1 $end
$var wire 1 B x2 $end
$var wire 1 ( x3 $end
$var wire 1 ) y $end
$upscope $end
$upscope $end
$upscope $end
$enddefinitions $end
#0
$dumpvars
0B
0A
0@
0?
1>
1=
0<
0;
0:
09
08
07
06
15
14
03
02
01
00
0/
0.
0-
0,
0+
0*
0)
0(
1'
0&
0%
0$
0#
0"
0!
$end
#10
1*
16
10
1+
1#
#15
1(
1/
0#
1"
#20
1)
0*
1?
06
19
00
1,
0+
1-
1#
#25
0)
1*
0?
16
09
10
0,
1+
0-
0'
0#
0"
1!
#30
1)
0*
1?
06
19
00
1,
0+
1-
1#
#35
0-
1&
0(
0/
1.
0#
1"
#40
1*
16
10
1+
1#
#45
0)
0?
00
09
04
11
0=
1$
#50
0*
06
01
0,
0&
1'
0.
0"
0!
#55
1,
0+
1-
1(
1/
1"
#60
0'
0"
1!
#65
14
1=
05
0>
0$
1%
#70
1*
17
0,
12
1+
0-
1'
0(
0/
0!
#75
1,
0+
1-
1(
1/
1"
#80
0*
07
02
0'
0"
1!
#85
1+
0-
1&
0(
0/
1.
1"
#90
04
0=
1$
#95
0,
0&
1'
0.
0"
0!
#100
1)
1@
1,
1<
0+
1-
1(
1/
1"
#105
0'
0"
1!
#110
0)
0@
0<
1+
0-
1&
0(
0/
1.
1"
