combination/mux4_1.v
module mux4_1 (y, x0, x1, x2, x3, c1, c0);
    input x0, x1, x2, x3, c1, c0;
    output y;
    
    wire w_A0, w_A1, w_A2, w_A3;
    wire w_r0, w_r2;

    wire w_N1, w_N0;

    not N1(w_N1, c1);
    not N0(w_N0, c0);

    and A0(w_A0, x0, w_N1, w_N0);
    and A1(w_A1, x1, w_N1, c0);
    and A2(w_A2, x2, c1, w_N0);
    and A3(w_A3, x3, c1, c0);

    or r0(w_r0, w_A0, w_A1);
    or r2(w_r2, w_A2, w_A3);
    or r3(y, w_r0, w_r2);
endmodule

combination/adder.v
module adder (Sum, Cout, Cin, A, B);
    input Cin, A, B;
    output Sum, Cout;

    wire w_xr0, w_A0, w_A1;

    xor xr0(w_xr0, A, B);
    xor xr1 (Sum, Cin, w_xr0);

    and A0(w_A0, w_xr0, Cin);
    and A1(w_A1, A, B);

    or r0(Cout, w_A0, w_A1);
endmodule

combination/1bit_ALU.v
`include "adder.v"
`include "mux4_1.v"

module one_bit_ALU (y, z, Cin, A, B, c1, c0);
    input Cin, A, B, c1, c0;
    output y, z;

    wire w_Sum, w_Cout;
    wire w_A0, w_N0, w_xr0;

    adder Adder1(w_Sum, w_Cout, Cin, A, B);
    and A0(w_A0, A, B);
    not N0(w_N0, A);
    xor xr0(w_xr0, A, B);

    mux4_1 mux1(y, w_Sum, w_A0, w_N0, 1'b0, c1, c0);
    mux4_1 mux2(z, w_Cout, 1'b0, 1'b0, w_xr0, c1, c0);
endmodule

combination/4bitALU.v
`include "1bit_ALU.v"

module four_bit_ALU (
    y, z,
    a, b,
    c1, c0
);

    input [3:0] a;
    input [3:0] b;

    output [3:0] y;
    output z;

    input c1, c0;

    wire w_z0, w_z1, w_z2;

    one_bit_ALU ALU0(y[0], w_z0, 1'b0, a[0], b[0], c1, c0);
    one_bit_ALU ALU1(y[1], w_z1, w_z0, a[1], b[1], c1, c0);
    one_bit_ALU ALU2(y[2], w_z2, w_z1, a[2], b[2], c1, c0);
    one_bit_ALU ALU3(y[3], z, w_z2, a[3], b[3], c1, c0);

endmodule

combination/stimulus_4bit_ALU.v
`include "4bitALU.v"

module stimulus_4bit_ALU;
    wire [3:0] y;
    wire z;

    reg [3:0] a;
    reg [3:0] b;

    reg c1, c0;

    four_bit_ALU four_bit_ALU(y, z, a, b, c1, c0);

    initial begin
        $dumpfile("4bitALU_TimingDiagram.vcd");
        $dumpvars(0, four_bit_ALU);
        a = 1'b0;
        b = 1'b0;
        c1 = 1'b0;
        c0 = 1'b0;
    end

    initial begin        
        repeat(8) begin
            b = 1'b0;
            repeat(8) begin
                #5 b = b + 1'b1;    
            end
            #5 a = a + 1'b1;
        end
        #5 a = a + 1'b1;
        a = 1'b0;

        c0 = 1'b1;
        repeat(8) begin
            b = 1'b0;
            repeat(8) begin
                #5 b = b + 1'b1;    
            end
            #5 a = a + 1'b1;
        end
        #5 a = a + 1'b1;
        a = 1'b0;

        c1 = 1'b1;
        c0 = 1'b0;
        repeat(8) begin
            b = 1'b0;
            repeat(8) begin
                #5 b = b + 1'b1;    
            end
            #5 a = a + 1'b1;
        end
        #5 a = a + 1'b1;
        a = 1'b0;

        c0 = 1'b1;
        repeat(8) begin
            b = 1'b0;
            repeat(8) begin
                #5 b = b + 1'b1;    
            end
            #5 a = a + 1'b1;
        end
        #5 a = a + 1'b1;
        
        #1200 $finish;
    end

    initial
        $monitor($time, " Output c1=%d, c0=%d, a=%b=%d, b=%b=%d, y=%b=%d, z=%d", c1, c0, a, a, b, b, y, y, z);
endmodule

combination/4bitALU_TimingDiagram.vcd
$date
	Sun Oct 17 22:04:14 2021
$end
$version
	Icarus Verilog
$end
$timescale
	1s
$end
$scope module stimulus_4bit_ALU $end
$scope module four_bit_ALU $end
$var wire 4 ! a [3:0] $end
$var wire 4 " b [3:0] $end
$var wire 1 # c0 $end
$var wire 1 $ c1 $end
$var wire 1 % z $end
$var wire 4 & y [3:0] $end
$var wire 1 ' w_z2 $end
$var wire 1 ( w_z1 $end
$var wire 1 ) w_z0 $end
$scope module ALU0 $end
$var wire 1 * A $end
$var wire 1 + B $end
$var wire 1 , Cin $end
$var wire 1 # c0 $end
$var wire 1 $ c1 $end
$var wire 1 - w_A0 $end
$var wire 1 . w_N0 $end
$var wire 1 / w_xr0 $end
$var wire 1 ) z $end
$var wire 1 0 y $end
$var wire 1 1 w_Sum $end
$var wire 1 2 w_Cout $end
$scope module Adder1 $end
$var wire 1 * A $end
$var wire 1 + B $end
$var wire 1 , Cin $end
$var wire 1 2 Cout $end
$var wire 1 1 Sum $end
$var wire 1 3 w_A0 $end
$var wire 1 4 w_A1 $end
$var wire 1 5 w_xr0 $end
$upscope $end
$scope module mux1 $end
$var wire 1 # c0 $end
$var wire 1 $ c1 $end
$var wire 1 6 w_A0 $end
$var wire 1 7 w_A1 $end
$var wire 1 8 w_A2 $end
$var wire 1 9 w_A3 $end
$var wire 1 : w_N0 $end
$var wire 1 ; w_N1 $end
$var wire 1 < w_r0 $end
$var wire 1 = w_r2 $end
$var wire 1 1 x0 $end
$var wire 1 - x1 $end
$var wire 1 . x2 $end
$var wire 1 > x3 $end
$var wire 1 0 y $end
$upscope $end
$scope module mux2 $end
$var wire 1 # c0 $end
$var wire 1 $ c1 $end
$var wire 1 ? w_A0 $end
$var wire 1 @ w_A1 $end
$var wire 1 A w_A2 $end
$var wire 1 B w_A3 $end
$var wire 1 C w_N0 $end
$var wire 1 D w_N1 $end
$var wire 1 E w_r0 $end
$var wire 1 F w_r2 $end
$var wire 1 2 x0 $end
$var wire 1 G x1 $end
$var wire 1 H x2 $end
$var wire 1 / x3 $end
$var wire 1 ) y $end
$upscope $end
$upscope $end
$scope module ALU1 $end
$var wire 1 I A $end
$var wire 1 J B $end
$var wire 1 ) Cin $end
$var wire 1 # c0 $end
$var wire 1 $ c1 $end
$var wire 1 K w_A0 $end
$var wire 1 L w_N0 $end
$var wire 1 M w_xr0 $end
$var wire 1 ( z $end
$var wire 1 N y $end
$var wire 1 O w_Sum $end
$var wire 1 P w_Cout $end
$scope module Adder1 $end
$var wire 1 I A $end
$var wire 1 J B $end
$var wire 1 ) Cin $end
$var wire 1 P Cout $end
$var wire 1 O Sum $end
$var wire 1 Q w_A0 $end
$var wire 1 R w_A1 $end
$var wire 1 S w_xr0 $end
$upscope $end
$scope module mux1 $end
$var wire 1 # c0 $end
$var wire 1 $ c1 $end
$var wire 1 T w_A0 $end
$var wire 1 U w_A1 $end
$var wire 1 V w_A2 $end
$var wire 1 W w_A3 $end
$var wire 1 X w_N0 $end
$var wire 1 Y w_N1 $end
$var wire 1 Z w_r0 $end
$var wire 1 [ w_r2 $end
$var wire 1 O x0 $end
$var wire 1 K x1 $end
$var wire 1 L x2 $end
$var wire 1 \ x3 $end
$var wire 1 N y $end
$upscope $end
$scope module mux2 $end
$var wire 1 # c0 $end
$var wire 1 $ c1 $end
$var wire 1 ] w_A0 $end
$var wire 1 ^ w_A1 $end
$var wire 1 _ w_A2 $end
$var wire 1 ` w_A3 $end
$var wire 1 a w_N0 $end
$var wire 1 b w_N1 $end
$var wire 1 c w_r0 $end
$var wire 1 d w_r2 $end
$var wire 1 P x0 $end
$var wire 1 e x1 $end
$var wire 1 f x2 $end
$var wire 1 M x3 $end
$var wire 1 ( y $end
$upscope $end
$upscope $end
$scope module ALU2 $end
$var wire 1 g A $end
$var wire 1 h B $end
$var wire 1 ( Cin $end
$var wire 1 # c0 $end
$var wire 1 $ c1 $end
$var wire 1 i w_A0 $end
$var wire 1 j w_N0 $end
$var wire 1 k w_xr0 $end
$var wire 1 ' z $end
$var wire 1 l y $end
$var wire 1 m w_Sum $end
$var wire 1 n w_Cout $end
$scope module Adder1 $end
$var wire 1 g A $end
$var wire 1 h B $end
$var wire 1 ( Cin $end
$var wire 1 n Cout $end
$var wire 1 m Sum $end
$var wire 1 o w_A0 $end
$var wire 1 p w_A1 $end
$var wire 1 q w_xr0 $end
$upscope $end
$scope module mux1 $end
$var wire 1 # c0 $end
$var wire 1 $ c1 $end
$var wire 1 r w_A0 $end
$var wire 1 s w_A1 $end
$var wire 1 t w_A2 $end
$var wire 1 u w_A3 $end
$var wire 1 v w_N0 $end
$var wire 1 w w_N1 $end
$var wire 1 x w_r0 $end
$var wire 1 y w_r2 $end
$var wire 1 m x0 $end
$var wire 1 i x1 $end
$var wire 1 j x2 $end
$var wire 1 z x3 $end
$var wire 1 l y $end
$upscope $end
$scope module mux2 $end
$var wire 1 # c0 $end
$var wire 1 $ c1 $end
$var wire 1 { w_A0 $end
$var wire 1 | w_A1 $end
$var wire 1 } w_A2 $end
$var wire 1 ~ w_A3 $end
$var wire 1 !" w_N0 $end
$var wire 1 "" w_N1 $end
$var wire 1 #" w_r0 $end
$var wire 1 $" w_r2 $end
$var wire 1 n x0 $end
$var wire 1 %" x1 $end
$var wire 1 &" x2 $end
$var wire 1 k x3 $end
$var wire 1 ' y $end
$upscope $end
$upscope $end
$scope module ALU3 $end
$var wire 1 '" A $end
$var wire 1 (" B $end
$var wire 1 ' Cin $end
$var wire 1 # c0 $end
$var wire 1 $ c1 $end
$var wire 1 )" w_A0 $end
$var wire 1 *" w_N0 $end
$var wire 1 +" w_xr0 $end
$var wire 1 % z $end
$var wire 1 ," y $end
$var wire 1 -" w_Sum $end
$var wire 1 ." w_Cout $end
$scope module Adder1 $end
$var wire 1 '" A $end
$var wire 1 (" B $end
$var wire 1 ' Cin $end
$var wire 1 ." Cout $end
$var wire 1 -" Sum $end
$var wire 1 /" w_A0 $end
$var wire 1 0" w_A1 $end
$var wire 1 1" w_xr0 $end
$upscope $end
$scope module mux1 $end
$var wire 1 # c0 $end
$var wire 1 $ c1 $end
$var wire 1 2" w_A0 $end
$var wire 1 3" w_A1 $end
$var wire 1 4" w_A2 $end
$var wire 1 5" w_A3 $end
$var wire 1 6" w_N0 $end
$var wire 1 7" w_N1 $end
$var wire 1 8" w_r0 $end
$var wire 1 9" w_r2 $end
$var wire 1 -" x0 $end
$var wire 1 )" x1 $end
$var wire 1 *" x2 $end
$var wire 1 :" x3 $end
$var wire 1 ," y $end
$upscope $end
$scope module mux2 $end
$var wire 1 # c0 $end
$var wire 1 $ c1 $end
$var wire 1 ;" w_A0 $end
$var wire 1 <" w_A1 $end
$var wire 1 =" w_A2 $end
$var wire 1 >" w_A3 $end
$var wire 1 ?" w_N0 $end
$var wire 1 @" w_N1 $end
$var wire 1 A" w_r0 $end
$var wire 1 B" w_r2 $end
$var wire 1 ." x0 $end
$var wire 1 C" x1 $end
$var wire 1 D" x2 $end
$var wire 1 +" x3 $end
$var wire 1 % y $end
$upscope $end
$upscope $end
$upscope $end
$upscope $end
$enddefinitions $end
#0
$dumpvars
0D"
0C"
0B"
0A"
1@"
1?"
0>"
0="
0<"
0;"
0:"
09"
08"
17"
16"
05"
04"
03"
02"
01"
00"
0/"
0."
0-"
0,"
0+"
1*"
0)"
0("
0'"
0&"
0%"
0$"
0#"
1""
1!"
0~
0}
0|
0{
0z
0y
0x
1w
1v
0u
0t
0s
0r
0q
0p
0o
0n
0m
0l
0k
1j
0i
0h
0g
0f
0e
0d
0c
1b
1a
0`
0_
0^
0]
0\
0[
0Z
1Y
1X
0W
0V
0U
0T
0S
0R
0Q
0P
0O
0N
0M
1L
0K
0J
0I
0H
0G
0F
0E
1D
1C
0B
0A
0@
0?
0>
0=
0<
1;
1:
09
08
07
06
05
04
03
02
01
00
0/
1.
0-
0,
0+
0*
0)
0(
0'
b0 &
0%
0$
0#
b0 "
b0 !
$end
#5
b1 &
10
1<
16
11
1/
15
1+
b1 "
#10
00
b10 &
1N
0<
1Z
06
1T
01
1O
0/
05
1M
1S
0+
1J
b10 "
#15
b11 &
10
1<
16
11
1/
15
1+
b11 "
#20
00
0N
b100 &
1l
0<
0Z
1x
06
0T
1r
01
0O
1m
0/
05
0M
0S
1k
1q
0+
0J
1h
b100 "
#25
b101 &
10
1<
16
11
1/
15
1+
b101 "
#30
00
b110 &
1N
0<
1Z
06
1T
01
1O
0/
05
1M
1S
0+
1J
b110 "
#35
b111 &
10
1<
16
11
1/
15
1+
b111 "
#40
00
0N
0l
b1000 &
1,"
0<
0Z
0x
18"
06
0T
0r
12"
01
0O
0m
1-"
0/
05
0M
0S
0k
0q
1+"
11"
0+
0J
0h
1("
b1000 "
#45
0,"
b1 &
10
08"
1<
02"
16
0-"
11
0+"
01"
0.
1/
15
0("
1*
b0 "
b1 !
#50
1N
1Z
1T
1O
b10 &
00
1)
0<
1E
06
1?
01
12
1-
0/
05
14
1+
b1 "
#55
0l
0x
0r
0m
0(
10
0)
b11 &
1N
0c
1<
0E
1Z
0]
16
0?
1T
0P
11
02
1O
0Q
0-
1/
15
04
1M
1S
0+
1J
b10 "
#60
1l
1x
1r
1m
1(
0N
1c
0Z
1]
0T
1P
0O
1Q
b100 &
00
1)
0<
1E
06
1?
01
12
1-
0/
05
14
1+
b11 "
#65
0,"
08"
02"
0-"
0(
0'
10
0)
0N
0c
b101 &
1l
0#"
1<
0E
0Z
0]
1x
0{
16
0?
0T
0P
1r
0n
11
02
0O
0Q
1m
0o
0-
1/
15
04
0M
0S
1k
1q
0+
0J
1h
b100 "
#70
1N
1Z
1T
1O
b110 &
00
1)
0<
1E
06
1?
01
12
1-
0/
05
14
1+
b101 "
#75
0,"
08"
02"
0-"
0'
1l
0#"
1x
0{
1r
0n
1m
0o
0(
10
0)
b111 &
1N
0c
1<
0E
1Z
0]
16
0?
1T
0P
11
02
1O
0Q
0-
1/
15
04
1M
1S
0+
1J
b110 "
#80
1,"
18"
12"
1-"
1'
0l
1#"
0x
1{
0r
1n
0m
1o
1(
0N
1c
0Z
1]
0T
1P
0O
1Q
b1000 &
00
1)
0<
1E
06
1?
01
12
1-
0/
05
14
1+
b111 "
#85
0(
0'
0%
10
0)
0N
0c
0l
0#"
b1001 &
1,"
0A"
1<
0E
0Z
0]
0x
0{
18"
0;"
16
0?
0T
0P
0r
0n
12"
0."
11
02
0O
0Q
0m
0o
1-"
0/"
0-
1/
15
04
0M
0S
0k
0q
1+"
11"
0+
0J
0h
1("
b1000 "
#90
0,"
00
b10 &
1N
08"
0<
1Z
02"
06
1T
0-"
01
1O
0+"
01"
1.
0/
05
0L
1M
1S
0("
0*
1I
b0 "
b10 !
#95
b11 &
10
1<
16
11
1/
15
1+
b1 "
#100
1l
1x
1r
1m
00
b100 &
0N
1(
0<
0Z
1c
06
0T
1]
01
0O
1P
0/
05
1K
0M
0S
1R
0+
1J
b10 "
#105
b101 &
10
1<
16
11
1/
15
1+
b11 "
#110
0,"
08"
02"
0-"
0'
00
1N
0(
b110 &
1l
0#"
0<
1Z
0c
1x
0{
06
1T
0]
1r
0n
01
1O
0P
1m
0o
0/
05
0K
1M
1S
0R
1k
1q
0+
0J
1h
b100 "
#115
b111 &
10
1<
16
11
1/
15
1+
b101 "
#120
1,"
18"
12"
1-"
1'
0l
1#"
0x
1{
0r
1n
0m
1o
00
b1000 &
0N
1(
0<
0Z
1c
06
0T
1]
01
0O
1P
0/
05
1K
0M
0S
1R
0+
1J
b110 "
#125
b1001 &
10
1<
16
11
1/
15
1+
b111 "
#130
0'
0%
00
1N
0(
0l
0#"
b1010 &
1,"
0A"
0<
1Z
0c
0x
0{
18"
0;"
06
1T
0]
0r
0n
12"
0."
01
1O
0P
0m
0o
1-"
0/"
0/
05
0K
1M
1S
0R
0k
0q
1+"
11"
0+
0J
0h
1("
b1000 "
#135
0,"
b11 &
10
08"
1<
02"
16
0-"
11
0+"
01"
0.
1/
15
0("
1*
b0 "
b11 !
#140
1l
1x
1r
1m
1(
0N
1c
0Z
1]
0T
1P
0O
1Q
b100 &
00
1)
0<
1E
06
1?
01
12
1-
0/
05
14
1+
b1 "
#145
10
0)
b101 &
0N
1<
0E
0Z
16
0?
0T
11
02
0O
0Q
0-
1/
15
04
1K
0M
0S
1R
0+
1J
b10 "
#150
1N
1Z
1T
1O
b110 &
00
1)
0<
1E
06
1?
01
12
1-
0/
05
14
1+
b11 "
#155
0,"
08"
02"
0-"
0'
10
0)
1N
0(
b111 &
1l
0#"
1<
0E
1Z
0c
1x
0{
16
0?
1T
0]
1r
0n
11
02
1O
0Q
0P
1m
0o
0-
1/
15
04
0K
1M
1S
0R
1k
1q
0+
0J
1h
b100 "
#160
1,"
18"
12"
1-"
1'
0l
1#"
0x
1{
0r
1n
0m
1o
1(
0N
1c
0Z
1]
0T
1P
0O
1Q
b1000 &
00
1)
0<
1E
06
1?
01
12
1-
0/
05
14
1+
b101 "
#165
10
0)
b1001 &
0N
1<
0E
0Z
16
0?
0T
11
02
0O
0Q
0-
1/
15
04
1K
0M
0S
1R
0+
1J
b110 "
#170
1N
1Z
1T
1O
b1010 &
00
1)
0<
1E
06
1?
01
12
1-
0/
05
14
1+
b111 "
#175
0'
0%
10
0)
1N
0(
0l
0#"
b1011 &
1,"
0A"
1<
0E
1Z
0c
0x
0{
18"
0;"
16
0?
1T
0]
0r
0n
12"
0."
11
02
1O
0Q
0P
0m
0o
1-"
0/"
0-
1/
15
04
0K
1M
1S
0R
0k
0q
1+"
11"
0+
0J
0h
1("
b1000 "
#180
0,"
00
0N
b100 &
1l
08"
0<
0Z
1x
02"
06
0T
1r
0-"
01
0O
1m
0+"
01"
1.
0/
05
1L
0M
0S
0j
1k
1q
0("
0*
0I
1g
b0 "
b100 !
#185
b101 &
10
1<
16
11
1/
15
1+
b1 "
#190
00
b110 &
1N
0<
1Z
06
1T
01
1O
0/
05
1M
1S
0+
1J
b10 "
#195
b111 &
10
1<
16
11
1/
15
1+
b11 "
#200
1,"
18"
12"
1-"
00
0N
b1000 &
0l
1'
0<
0Z
0x
1#"
06
0T
0r
1{
01
0O
0m
1n
0/
05
0M
0S
1i
0k
0q
1p
0+
0J
1h
b100 "
#205
b1001 &
10
1<
16
11
1/
15
1+
b101 "
#210
00
b1010 &
1N
0<
1Z
06
1T
01
1O
0/
05
1M
1S
0+
1J
b110 "
#215
b1011 &
10
1<
16
11
1/
15
1+
b111 "
#220
0%
00
0N
1l
0'
b1100 &
1,"
0A"
0<
0Z
1x
0#"
18"
0;"
06
0T
1r
0{
12"
0."
01
0O
1m
0n
1-"
0/"
0/
05
0M
0S
0i
1k
1q
0p
1+"
11"
0+
0J
0h
1("
b1000 "
#225
0,"
b101 &
10
08"
1<
02"
16
0-"
11
0+"
01"
0.
1/
15
0("
1*
b0 "
b101 !
#230
1N
1Z
1T
1O
b110 &
00
1)
0<
1E
06
1?
01
12
1-
0/
05
14
1+
b1 "
#235
0,"
08"
02"
0-"
0'
1l
0#"
1x
0{
1r
0n
1m
0o
0(
10
0)
b111 &
1N
0c
1<
0E
1Z
0]
16
0?
1T
0P
11
02
1O
0Q
0-
1/
15
04
1M
1S
0+
1J
b10 "
#240
1,"
18"
12"
1-"
1'
0l
1#"
0x
1{
0r
1n
0m
1o
1(
0N
1c
0Z
1]
0T
1P
0O
1Q
b1000 &
00
1)
0<
1E
06
1?
01
12
1-
0/
05
14
1+
b11 "
#245
0(
10
0)
0N
0c
b1001 &
0l
1<
0E
0Z
0]
0x
16
0?
0T
0P
0r
11
02
0O
0Q
0m
0o
0-
1/
15
04
0M
0S
1i
0k
0q
1p
0+
0J
1h
b100 "
#250
1N
1Z
1T
1O
b1010 &
00
1)
0<
1E
06
1?
01
12
1-
0/
05
14
1+
b101 "
#255
0l
0x
0r
0m
0(
10
0)
b1011 &
1N
0c
1<
0E
1Z
0]
16
0?
1T
0P
11
02
1O
0Q
0-
1/
15
04
1M
1S
0+
1J
b110 "
#260
1l
1x
1r
1m
1(
0N
1c
0Z
1]
0T
1P
0O
1Q
b1100 &
00
1)
0<
1E
06
1?
01
12
1-
0/
05
14
1+
b111 "
#265
0(
0%
10
0)
0N
0c
1l
0'
b1101 &
1,"
0A"
1<
0E
0Z
0]
1x
0#"
18"
0;"
16
0?
0T
0P
1r
0{
12"
0."
11
02
0O
0Q
1m
0o
0n
1-"
0/"
0-
1/
15
04
0M
0S
0i
1k
1q
0p
1+"
11"
0+
0J
0h
1("
b1000 "
#270
0,"
00
b110 &
1N
08"
0<
1Z
02"
06
1T
0-"
01
1O
0+"
01"
1.
0/
05
0L
1M
1S
0("
0*
1I
b0 "
b110 !
#275
b111 &
10
1<
16
11
1/
15
1+
b1 "
#280
1,"
18"
12"
1-"
1'
0l
1#"
0x
1{
0r
1n
0m
1o
00
b1000 &
0N
1(
0<
0Z
1c
06
0T
1]
01
0O
1P
0/
05
1K
0M
0S
1R
0+
1J
b10 "
#285
b1001 &
10
1<
16
11
1/
15
1+
b11 "
#290
00
1N
0(
b1010 &
0l
0<
1Z
0c
0x
06
1T
0]
0r
01
1O
0P
0m
0o
0/
05
0K
1M
1S
0R
1i
0k
0q
1p
0+
0J
1h
b100 "
#295
b1011 &
10
1<
16
11
1/
15
1+
b101 "
#300
1l
1x
1r
1m
00
b1100 &
0N
1(
0<
0Z
1c
06
0T
1]
01
0O
1P
0/
05
1K
0M
0S
1R
0+
1J
b110 "
#305
b1101 &
10
1<
16
11
1/
15
1+
b111 "
#310
0%
00
1N
0(
1l
0'
b1110 &
1,"
0A"
0<
1Z
0c
1x
0#"
18"
0;"
06
1T
0]
1r
0{
12"
0."
01
1O
0P
1m
0o
0n
1-"
0/"
0/
05
0K
1M
1S
0R
0i
1k
1q
0p
1+"
11"
0+
0J
0h
1("
b1000 "
#315
0,"
b111 &
10
08"
1<
02"
16
0-"
11
0+"
01"
0.
1/
15
0("
1*
b0 "
b111 !
#320
1,"
18"
12"
1-"
1'
0l
1#"
0x
1{
0r
1n
0m
1o
1(
0N
1c
0Z
1]
0T
1P
0O
1Q
b1000 &
00
1)
0<
1E
06
1?
01
12
1-
0/
05
14
1+
b1 "
#325
10
0)
b1001 &
0N
1<
0E
0Z
16
0?
0T
11
02
0O
0Q
0-
1/
15
04
1K
0M
0S
1R
0+
1J
b10 "
#330
1N
1Z
1T
1O
b1010 &
00
1)
0<
1E
06
1?
01
12
1-
0/
05
14
1+
b11 "
#335
10
0)
1N
0(
b1011 &
0l
1<
0E
1Z
0c
0x
16
0?
1T
0]
0r
11
02
1O
0Q
0P
0m
0o
0-
1/
15
04
0K
1M
1S
0R
1i
0k
0q
1p
0+
0J
1h
b100 "
#340
1l
1x
1r
1m
1(
0N
1c
0Z
1]
0T
1P
0O
1Q
b1100 &
00
1)
0<
1E
06
1?
01
12
1-
0/
05
14
1+
b101 "
#345
10
0)
b1101 &
0N
1<
0E
0Z
16
0?
0T
11
02
0O
0Q
0-
1/
15
04
1K
0M
0S
1R
0+
1J
b110 "
#350
1N
1Z
1T
1O
b1110 &
00
1)
0<
1E
06
1?
01
12
1-
0/
05
14
1+
b111 "
#355
0%
10
0)
1N
0(
1l
0'
b1111 &
1,"
0A"
1<
0E
1Z
0c
1x
0#"
18"
0;"
16
0?
1T
0]
1r
0{
12"
0."
11
02
1O
0Q
0P
1m
0o
0n
1-"
0/"
0-
1/
15
04
0K
1M
1S
0R
0i
1k
1q
0p
1+"
11"
0+
0J
0h
1("
b1000 "
#360
00
0N
0l
b0 &
0,"
1%
0<
0Z
0x
08"
1A"
06
0T
0r
02"
1;"
01
0O
0m
0-"
1."
1.
0/
05
1L
0M
0S
1j
0k
0q
1)"
0*"
0+"
01"
10"
0*
0I
0g
1'"
b1000 !
#365
0%
b0 &
0,"
0A"
0."
08"
0;"
0)"
1*"
00"
0("
0:
0C
0X
0a
0v
0!"
06"
03"
0?"
0'"
b0 "
1#
b0 !
#370
11
1/
15
1+
b1 "
#375
01
1O
0/
05
1M
1S
0+
1J
b10 "
#380
11
1/
15
1+
b11 "
#385
01
0O
1m
0/
05
0M
0S
1k
1q
0+
0J
1h
b100 "
#390
11
1/
15
1+
b101 "
#395
01
1O
0/
05
1M
1S
0+
1J
b110 "
#400
11
1/
15
1+
b111 "
#405
01
0O
0m
1-"
0/
05
0M
0S
0k
0q
1+"
11"
0+
0J
0h
1("
b1000 "
#410
0-"
11
0+"
01"
0.
1/
15
0("
1*
b0 "
b1 !
#415
b1 &
10
1<
17
01
12
1-
0/
05
14
1+
b1 "
#420
b0 &
00
0<
07
11
02
1O
0-
1/
15
04
1M
1S
0+
1J
b10 "
#425
b1 &
10
1<
17
01
12
1-
0/
05
14
1+
b11 "
#430
b0 &
00
0<
07
11
02
0O
1m
0-
1/
15
04
0M
0S
1k
1q
0+
0J
1h
b100 "
#435
b1 &
10
1<
17
01
12
1-
0/
05
14
1+
b101 "
#440
b0 &
00
0<
07
11
02
1O
0-
1/
15
04
1M
1S
0+
1J
b110 "
#445
b1 &
10
1<
17
01
12
1-
0/
05
14
1+
b111 "
#450
b0 &
00
0<
07
11
02
0O
0m
1-"
0-
1/
15
04
0M
0S
0k
0q
1+"
11"
0+
0J
0h
1("
b1000 "
#455
0-"
01
1O
0+"
01"
1.
0/
05
0L
1M
1S
0("
0*
1I
b0 "
b10 !
#460
11
1/
15
1+
b1 "
#465
b10 &
1N
1Z
01
1U
0O
1P
0/
05
1K
0M
0S
1R
0+
1J
b10 "
#470
11
1/
15
1+
b11 "
#475
b0 &
0N
0Z
01
0U
1O
0P
1m
0/
05
0K
1M
1S
0R
1k
1q
0+
0J
1h
b100 "
#480
11
1/
15
1+
b101 "
#485
b10 &
1N
1Z
01
1U
0O
1P
0/
05
1K
0M
0S
1R
0+
1J
b110 "
#490
11
1/
15
1+
b111 "
#495
b0 &
0N
0Z
01
0U
1O
0P
0m
1-"
0/
05
0K
1M
1S
0R
0k
0q
1+"
11"
0+
0J
0h
1("
b1000 "
#500
0-"
11
0+"
01"
0.
1/
15
0("
1*
b0 "
b11 !
#505
b1 &
10
1<
17
01
12
1-
0/
05
14
1+
b1 "
#510
00
b10 &
1N
0<
1Z
07
11
02
1U
0O
1P
0-
1/
15
04
1K
0M
0S
1R
0+
1J
b10 "
#515
b11 &
10
1<
17
01
12
1-
0/
05
14
1+
b11 "
#520
00
b0 &
0N
0<
0Z
07
11
02
0U
1O
0P
1m
0-
1/
15
04
0K
1M
1S
0R
1k
1q
0+
0J
1h
b100 "
#525
b1 &
10
1<
17
01
12
1-
0/
05
14
1+
b101 "
#530
00
b10 &
1N
0<
1Z
07
11
02
1U
0O
1P
0-
1/
15
04
1K
0M
0S
1R
0+
1J
b110 "
#535
b11 &
10
1<
17
01
12
1-
0/
05
14
1+
b111 "
#540
00
b0 &
0N
0<
0Z
07
11
02
0U
1O
0P
0m
1-"
0-
1/
15
04
0K
1M
1S
0R
0k
0q
1+"
11"
0+
0J
0h
1("
b1000 "
#545
0-"
01
0O
1m
0+"
01"
1.
0/
05
1L
0M
0S
0j
1k
1q
0("
0*
0I
1g
b0 "
b100 !
#550
11
1/
15
1+
b1 "
#555
01
1O
0/
05
1M
1S
0+
1J
b10 "
#560
11
1/
15
1+
b11 "
#565
b100 &
1l
1x
01
0O
1s
0m
1n
0/
05
0M
0S
1i
0k
0q
1p
0+
0J
1h
b100 "
#570
11
1/
15
1+
b101 "
#575
01
1O
0/
05
1M
1S
0+
1J
b110 "
#580
11
1/
15
1+
b111 "
#585
b0 &
0l
0x
01
0O
0s
1m
0n
1-"
0/
05
0M
0S
0i
1k
1q
0p
1+"
11"
0+
0J
0h
1("
b1000 "
#590
0-"
11
0+"
01"
0.
1/
15
0("
1*
b0 "
b101 !
#595
b1 &
10
1<
17
01
12
1-
0/
05
14
1+
b1 "
#600
b0 &
00
0<
07
11
02
1O
0-
1/
15
04
1M
1S
0+
1J
b10 "
#605
b1 &
10
1<
17
01
12
1-
0/
05
14
1+
b11 "
#610
00
b100 &
1l
0<
1x
07
11
02
0O
1s
0m
1n
0-
1/
15
04
0M
0S
1i
0k
0q
1p
0+
0J
1h
b100 "
#615
b101 &
10
1<
17
01
12
1-
0/
05
14
1+
b101 "
#620
b100 &
00
0<
07
11
02
1O
0-
1/
15
04
1M
1S
0+
1J
b110 "
#625
b101 &
10
1<
17
01
12
1-
0/
05
14
1+
b111 "
#630
00
b0 &
0l
0<
0x
07
11
02
0O
0s
1m
0n
1-"
0-
1/
15
04
0M
0S
0i
1k
1q
0p
1+"
11"
0+
0J
0h
1("
b1000 "
#635
0-"
01
1O
0+"
01"
1.
0/
05
0L
1M
1S
0("
0*
1I
b0 "
b110 !
#640
11
1/
15
1+
b1 "
#645
b10 &
1N
1Z
01
1U
0O
1P
0/
05
1K
0M
0S
1R
0+
1J
b10 "
#650
11
1/
15
1+
b11 "
#655
0N
b100 &
1l
0Z
1x
01
0U
1O
0P
1s
0m
1n
0/
05
0K
1M
1S
0R
1i
0k
0q
1p
0+
0J
1h
b100 "
#660
11
1/
15
1+
b101 "
#665
b110 &
1N
1Z
01
1U
0O
1P
0/
05
1K
0M
0S
1R
0+
1J
b110 "
#670
11
1/
15
1+
b111 "
#675
0N
b0 &
0l
0Z
0x
01
0U
1O
0P
0s
1m
0n
1-"
0/
05
0K
1M
1S
0R
0i
1k
1q
0p
1+"
11"
0+
0J
0h
1("
b1000 "
#680
0-"
11
0+"
01"
0.
1/
15
0("
1*
b0 "
b111 !
#685
b1 &
10
1<
17
01
12
1-
0/
05
14
1+
b1 "
#690
00
b10 &
1N
0<
1Z
07
11
02
1U
0O
1P
0-
1/
15
04
1K
0M
0S
1R
0+
1J
b10 "
#695
b11 &
10
1<
17
01
12
1-
0/
05
14
1+
b11 "
#700
00
0N
b100 &
1l
0<
0Z
1x
07
11
02
0U
1O
0P
1s
0m
1n
0-
1/
15
04
0K
1M
1S
0R
1i
0k
0q
1p
0+
0J
1h
b100 "
#705
b101 &
10
1<
17
01
12
1-
0/
05
14
1+
b101 "
