sequential/4/D_FF.v
module D_FF(q,d,clk,reset);
	output q;
	input d,clk,reset;
	reg q;
	always @ (posedge reset or negedge clk)
	if(reset)
		q <= 1'b0;
	else
		q <= d;
endmodule

sequential/4/two_way_count_g.v
`include "D_FF.v"

module two_way_count_g(l ,x, clk, reset);
    input x, clk, reset;
    wire [1:0] q;
    
    wire w_xor0, w_xor1, w_not0;

    xor xor1(w_xor1, q[0], q[1]);
    xor xor0(w_xor0, x, w_xor1);
    D_FF D0(q[0], w_not0, clk, reset);

    not not0(w_not0, q[0]);
    D_FF D1(q[1], w_xor0, clk, reset);

    output l;
    wire w_not1, w_and0;    

    not not1(w_not1,q[1]);
    and and1(w_and0, w_not1,q[0]);
    and and2(l,x,w_and0);

endmodule

sequential/4/stimulus_two_way_count_g.v
`include "two_way_count_g.v"

module stimulus_two_way_count_g;
    reg x;
    reg clk, reset;
    wire [1:0]q;

    wire l;
    assign L = l;

    two_way_count_g c0(q, l, x, clk, reset);

    initial begin
		$dumpfile("two_way_count_g.vcd");
        $dumpvars(0, c0);
		clk = 1'b0;
        x = 1'b0;
        reset = 1'b0;
	end
	always
		#5	clk = ~clk;
    // TODO: Test two count
	initial begin
        // x = 1'b0;
reset = 1'b1;
x = 1'b0;
#50 reset = 1'b0;
#50 x = 1'b1;
#0 reset = 1'b1;
#25 reset = 1'b0;
#50 reset = 1'b0;
#50 $finish;
	end
	
	initial
		$monitor($time, " output L = %d  q = %d (%d%d) reset = %d x = %d",L, q, q[1], q[0], reset, x);
endmodule

sequential/4/two_way_count_g.vcd
$date
	Sun Oct 17 18:22:38 2021
$end
$version
	Icarus Verilog
$end
$timescale
	1s
$end
$scope module stimulus_two_way_count_g $end
$scope module c0 $end
$var wire 1 ! clk $end
$var wire 1 " l $end
$var wire 1 # reset $end
$var wire 1 $ w_and0 $end
$var wire 1 % w_not0 $end
$var wire 1 & w_not1 $end
$var wire 1 ' w_xor0 $end
$var wire 1 ( w_xor1 $end
$var wire 1 ) x $end
$var wire 2 * q [1:0] $end
$scope module D0 $end
$var wire 1 ! clk $end
$var wire 1 % d $end
$var wire 1 # reset $end
$var reg 1 + q $end
$upscope $end
$scope module D1 $end
$var wire 1 ! clk $end
$var wire 1 ' d $end
$var wire 1 # reset $end
$var reg 1 , q $end
$upscope $end
$upscope $end
$upscope $end
$enddefinitions $end
#0
$dumpvars
0,
0+
b0 *
0)
0(
0'
1&
1%
0$
1#
0"
0!
$end
#5
1!
#10
0!
#15
1!
#20
0!
#25
1!
#30
0!
#35
1!
#40
0!
#45
1!
#50
1'
1$
0%
1(
b1 *
1+
0!
0#
#55
1!
#60
0$
1%
0&
0+
b10 *
1,
0!
#65
1!
#70
0'
0%
0(
b11 *
1+
0!
#75
1!
#80
1%
1&
0+
b0 *
0,
0!
#85
1!
#90
1'
1$
0%
1(
b1 *
1+
0!
#95
1!
#100
0$
1%
0(
b0 *
0+
1#
1'
0"
0!
1)
#105
1!
#110
0!
#115
1!
#120
0!
#125
1!
0#
#130
0%
0&
1+
b11 *
1,
0!
#135
1!
#140
0'
1%
1(
b10 *
0+
0!
#145
1!
#150
1"
1$
0%
1&
1+
b1 *
0,
0!
#155
1!
#160
0"
1'
0$
1%
0(
b0 *
0+
0!
#165
1!
#170
0%
0&
1+
b11 *
1,
0!
#175
1!
#180
0'
1%
1(
b10 *
0+
0!
#185
1!
#190
1"
1$
0%
1&
1+
b1 *
0,
0!
#195
1!
#200
0"
1'
0$
1%
0(
b0 *
0+
0!
#205
1!
#210
0%
0&
1+
b11 *
1,
0!
#215
1!
#220
0'
1%
1(
b10 *
0+
0!
